numipulator.py
numipulator-0.2.1.dist-info/LICENSE
numipulator-0.2.1.dist-info/METADATA
numipulator-0.2.1.dist-info/WHEEL
numipulator-0.2.1.dist-info/top_level.txt
numipulator-0.2.1.dist-info/RECORD
